{
  "top_code": "import Mathlib\nuniverse u v w u_1 u_2 u_3 u\u2081 u\u2082 u\u2083\nset_option maxHeartbeats 10000000\nset_option linter.unreachableTactic false\n",
  "task": "lean_from_json_structured",
  "result": "success",
  "lean_code": "theorem Int.dvd_of_dvd_mul_right : \u2200 {n : \u2124}, 12 \u2223 n \u2192 3 \u2223 n :=\n    by\n    intro n\n    have assert_3615068981003539281 : 12 \u2223 n \u2192 \u2203 (q : \u2124), n = 12 * q :=\n      by\n      intro a\n      exact a\n    have assert_12817895613275285507 : \u2200 (q : \u2124), 12 \u2223 n \u2192 n = 3 * (4 * q) :=\n      by\n      intro q a\n      simp_all only [forall_const]\n      obtain \u27e8w, h\u27e9 := assert_3615068981003539281\n      subst h\n      simp_all only [dvd_mul_right]\n      sorry\n    let k : \u2124 := 4 * q\n    have assert_8567014919718961824 : 12 \u2223 n \u2192 \u2203 (k : \u2124), n = 3 * k :=\n      by\n      intro a\n      simp_all only [forall_const]\n      obtain \u27e8w, h\u27e9 := assert_3615068981003539281\n      subst h\n      simp_all only [dvd_mul_right]\n      apply Exists.intro\n      \u00b7 apply assert_12817895613275285507\n        exact n\n    exact fun a =>\n      assert_8567014919718961824\n        (assert_3615068981003539281 (assert_3615068981003539281 (assert_3615068981003539281 a)))",
  "json_structured": {
    "document": [
      {
        "type": "Theorem",
        "proof": {
          "type": "Proof",
          "proof_steps": [
            {
              "type": "Paragraph",
              "text": "The statement \"integer x is divisible by integer y\" is equivalent to \"there must exist an integer q such that x = y * q\"."
            },
            {
              "type": "assert_statement",
              "results_used": [
                {
                  "statement": "n is divisible by 12"
                }
              ],
              "proof_method": "deduction from assumption",
              "label": "eq:n_divisible_by_12",
              "claim": "there exists an integer q such that n = 12 * q"
            },
            {
              "type": "assert_statement",
              "results_used": [
                {
                  "statement": "12 = 3 * 4"
                },
                {
                  "target_identifier": "eq:n_divisible_by_12",
                  "statement": "n = 12 * q"
                }
              ],
              "proof_method": "algebraic manipulation",
              "label": "eq:rewritten_n",
              "claim": "n = 3 * (4 * q)"
            },
            {
              "variable_type": "integer",
              "variable_name": "k",
              "value": "4 * q",
              "type": "let_statement",
              "statement": "Let integer k = 4 * q, since the product of two integer is an integer.",
              "properties": "since the product of two integers is an integer",
              "label": "eq:define_k"
            },
            {
              "type": "assert_statement",
              "results_used": [
                {
                  "target_identifier": "eq:rewritten_n",
                  "statement": "n = 3 * (4 * q)"
                },
                {
                  "target_identifier": "eq:define_k",
                  "statement": "k = 4 * q"
                }
              ],
              "proof_method": "substitution",
              "claim": "n = 3 * k for some integer k"
            },
            {
              "type": "conclude_statement",
              "claim": "n is divisible by 3, since there exists an integer k such that n = 3 * k."
            }
          ],
          "claim_label": "thm:divisibility_by_12_implies_3"
        },
        "label": "thm:divisibility_by_12_implies_3",
        "hypothesis": [
          {
            "type": "assume_statement",
            "assumption": "an integer n is divisible by 12"
          }
        ],
        "header": "Theorem",
        "claim": "n is divisible by 3"
      }
    ]
  },
  "greedy": false,
  "declarations": [
    "Int.dvd_of_dvd_mul_right"
  ]
}